VbeeLogger/VbeeLogger.py
VbeeLogger/__init__.py
VbeeLogger/constant.py
vbee_logger-0.1.7.dist-info/LICENSE
vbee_logger-0.1.7.dist-info/METADATA
vbee_logger-0.1.7.dist-info/WHEEL
vbee_logger-0.1.7.dist-info/top_level.txt
vbee_logger-0.1.7.dist-info/RECORD
