Metadata-Version: 2.1
Name: vbee-logger
Version: 0.1.7
Summary: Vbee python logging
Home-page: UNKNOWN
Author: Vbee
License: UNKNOWN
Platform: UNKNOWN
Classifier: Programming Language :: Python :: 3
Classifier: License :: OSI Approved :: MIT License
Classifier: Operating System :: OS Independent
Requires-Python: >=3.6
